{
  "list": [
    {
      "star": "false",
      "id": "0101",
      "group": "Супы",
      "title": "Суп с фрикадельками",
      "description": "Суп с фрикадельками из индейки",
      "veg": "false",
      "ingredients": [
        "индейка: 500гр",
        "гречневая крупа: 100гр",
        "средний картофель: 4-5 шт",
        "лук: 1шт",
        "морковь: 1шт",
        "зелень: 3-4 веточки",
        "немного соли"
      ],
      "steps": "Индейку перемолоть в фарш, немного посолить, из фарша сделать небольшие шарики, то есть фрикадельки.\nВ трёхлитровую кастрюлю налить фильтрованной воды.\nОчистить и соломкой порезать морковь и картофель.\nЛук нашинковать.\nВсыпать все овощи в кастрюлю и подождать пока закипит вода.\nПеребрать и промыть гречневую крупу.\nВ кипящую воду добавить фрикадельки и крупу, посолить.\nУменьшить огонь и варить 15 минут.\nВ готовое блюдо положить немного порезанной зелени.",
      "img": ""
    }
  ,{
      "star": "false",
      "id": "0102",
      "group": "Супы",
      "title": "Суп с овощами и кусочками говядины",
      "description": "Суп с овощами и кусочками говядины",
      "veg": "false",
      "ingredients": [
        "нежирная говядина: 500г р",
        "цветная капуста: 200 гр.",
        "средний кабачок: 1 шт",
        "крупный картофель: 3 шт",
        "морковь: 1 шт",
        "луковица: 1 шт",
        "соль по вкусу"
      ],
      "steps": "Для приготовления супа из говядины нам понадобится второй бульон.\nКубиками нарежем кабачок, морковь и картофель.\nЛуковицу нашинкуем, а цветную капусту порежем.\nВсе овощи добавим в трёхлитровую кастрюлю и даём закипеть.\nВарим 15 минут.\nВ суп добавляем предварительно сваренные и порезанные кусочки говядины, щепотку соли.\nДержим на огне ещё 3 минуты.\n",
      "img": ""
    }

  ,{
      "star": "false",
      "id": "0103",
      "group": "Супы",
      "title": "Суп-пюре из рыбы",
      "description": "Суп-пюре для любителей рыбы",
      "veg": "false",
      "ingredients": [
        "хек : 2 шт",
        "средний картофель: 6 шт",
        "морковь: 1 шт",
        "луковица: 1 шт",
        "пшено: 50 гр",
        "оливковое масло: 1ст.л.",
        "зелень",
        "соль по вкусу"
      ],
      "steps": "Хека очищаем, моем, нарезаем на небольшие куски и в течение 7 минут варим.\nСливаем воду и наливаем новую.\nВ кастрюлю помещаем рыбу и в течение 20 минут варим.\nЗатем вынимаем рыбу и с помощью дуршлага процеживаем бульон.\nДобавляем в него очищенные и порезанные овощи.\nПшеничную крупу перебираем и моем, всыпаем её в кастрюлю.\nВарим суп 15 минут.\nПосле того как овощи дошли до полуготовности, добавим рыбу и проварим ещё 5 минут.\nВливаем оливковое масло, а после того, как суп немного остынет, измельчаем его в блендере.\nСолим суп-пюре и украшаем зеленью",
      "img": ""
    }
  ,{
      "star": "false",
      "id": "0104",
      "group": "Супы",
      "title": "Морковно-картофельный суп-пюре",
      "description": "",
      "veg": "true",
      "ingredients": [
        "картофель : 4 шт",
        "морковь: 1 шт",
        "луковица: 1 шт",
        "оливковое масло: 1ст.л.",
        "зелень",
        "соль по вкусу"
      ],
      "steps": "Все овощи помыть и очистить.\nКартофель и морковь нарезать кубиками.\nЛуковицу нашинковать.\nВ кастрюлю налить воды, добавить все овощи, довести до кипения.\nВарить на слабом огне 30 минут.\nСложить все ингредиенты в комбайн и измельчить.\nВ готовый суп-пюре добавить оливковое масло и украсить зеленью.",
      "img": ""
    }
  ,{
      "star": "false",
      "id": "0105",
      "group": "Супы",
      "title": "Суп-пюре из кабачков",
      "description": "",
      "veg": "true",
      "ingredients": [
        "картофель : 4 шт",
        "кабачок: 2 шт",
        "корень имбиря: 1 ч.л.",
        "растительное масло: 1ст.л.",
        "зелень"
      ],
      "steps": "Все овощи помыть, очистить, нарезать кубиками и высыпать в кипящую кастрюлю с водой.\nВарить овощи 15 минут.\nКорень имбиря и зелень мелко порезать и добавить в суп.\nПриготовить пюре из сваренных овощей при помощи блендера.\nЗаправить суп-пюре растительным маслом.",
      "img": ""
    }
  ,{
      "star": "false",
      "id": "0201",
      "group": "Вторые блюда",
      "title": "Гуляшь из говядины",
      "description": "",
      "veg": "false",
      "ingredients": [
        "говядина : 1 кг",
        "луковица: 2 шт",
        "морковь: 1 шт",
        "лавровый лист",
        "мука: 1ст.л.",
        "соль по вкусу"
      ],
      "steps": "Нарезаем кусочки мяса размером 3Х4 см и кладём в сотейник.\nМясо заливаем водой.\nВарим 5 минут, сливаем первый бульон.\nЗаново заливаем мясо водой и готовим 25 минут.\nМорковь чистим и натираем её на тёрке.\nРежем лук.\nВсе овощи всыпаем в кастрюлю, солим, кладём ложку муки.\nНакрываем сотейник крышкой и тушим мясо 8 минут до готовности",
      "img": ""
    }

  ,{
      "star": "false",
      "id": "0202",
      "group": "Вторые блюда",
      "title": "Котлеты",
      "description": "Котлеты из говядины и свинины",
      "veg": "false",
      "ingredients": [
        "говядина : 500 гр",
        "нежирная свинина : 500 гр",
        "луковица: 1 шт",
        "морковь: 1 шт",
        "яйцо: 1 шт",
        "соль по вкусу"
      ],
      "steps": "Мясо нежирной свинины и говядины измельчаем на фарш.\nМорковь натираем, а лук шинкуем.\nВсе овощи и яйцо добавляем в фарш, солим и формируем котлеты.\nВыкладываем котлеты на сковороду, наливаем небольшое количество воды, накрываем сковороду крышкой.\nУменьшаем огонь и тушим котлеты 15 минут.",
      "img": ""
    }

  ,{
      "star": "false",
      "id": "0203",
      "group": "Вторые блюда",
      "title": "Рагу в горшочке",
      "description": "",
      "veg": "false",
      "ingredients": [
        "индейка: 500 гр",
        "крупный картофель: 5 шт",
        "цветная капуста: 300 гр",
        "кабачок: 1 шт ",
        "луковица: 1 шт",
        "морковь: 2 шт",
        "сливочное масло: 1 ст.л.",
        "несколько веточек петрушки и укропа",
        "соль по вкусу"
      ],
      "steps": "Филе индейки моем, солим, кладём в фольгу и запекаем при 180 градусах в течение 50 минут.\nВсе овощи моем и чистим.\nКубиками нарезаем кабачок и картофель, шинкуем лук, натираем на тёрке морковь, цветную капусту измельчаем.\nВсыпаем все овощи в сковородку и тушим до полуготовности.\nТушёные овощи и порезанные кусочки филе выкладываем в горшочки, добавляем 100 мл воды, солим и заправляем сливочным маслом.\nОтправляем на 7 минут в разогретую до 200 градусов духовку.\nПриготовленное блюдо посыпаем зеленью",
      "img": ""
    }

  ,{
      "star": "false",
      "id": "0204",
      "group": "Вторые блюда",
      "title": "Тефтели",
      "description": "",
      "veg": "false",
      "ingredients": [
        "куриное филе: 500 гр",
        "гречневая крупа: 100 гр",
        "яичный желток: 1 шт",
        "луковица: 1 шт",
        "морковь: 1 шт",
        "сметана 15%: 1 ст.л.",
        "твердый сыр: 50 гр",
        "несколько веточек петрушки и укропа",
        "соль, перец по вкусу"
      ],
      "steps": "Отвариваем до полуготовности гречневую крупу.\nВсе овощи моем и измельчаем.\nКуриное филе перекручиваем на фарш.\nСмешиваем все ингредиенты, добавляем яичный желток, немного солим, перчим и формируем тефтели.\nВ сковороду наливаем воду так, чтобы она покрыла тефтели, кладём сметану, солим по вкусу и тушим на сковородке под крышкой 25 минут.\nПосыпаем зеленью и тёртым сыром готовые тефтели.",
      "img": ""
    }


  ,{
      "star": "false",
      "id": "0205",
      "group": "Вторые блюда",
      "title": "Паровой омлет",
      "description": "",
      "veg": "false",
      "ingredients": [
        "яйца: 2 шт",
        "молоко: 50 гр",
        "сливочное масло: 5 гр",
        "соль, перец по вкусу"
      ],
      "steps": "Разбиваем яйца в миску, добавляем соль и взбиваем.\nПродолжаем мешать, вливая тонкой струйкой молоко.\nСмазываем сливочным маслом форму и заполняем её яичной смесью.\nВ кастрюлю наливаем 1/3 воды, сверху ставим дуршлаг, а на дуршлаг форму с омлетом.\nВарим омлет на пару 45 минут и следим, чтобы вода в кастрюле не выкипела. Или воспользуемся пароваркой.",
      "img": ""
    }

  ,{
      "star": "false",
      "id": "0206",
      "group": "Вторые блюда",
      "title": "Хек с овощами на пару",
      "description": "",
      "veg": "false",
      "ingredients": [
        "хек: 2 шт",
        "картофель: 4 шт",
        "цветная капуста: 200 гр",
        "морковь: 1 шт",
        "оливковое масло: 1 ст.л.",
        "соль, перец по вкусу"
      ],
      "steps": "Хека моем, очищаем от шелухи, отрезаем голову и хвост, удаляем внутренности.\nРежем рыбу на небольшие кусочки, солим.\nОвощи моем, чистим, режем, солим и перчим.\nНа дно пароварки выкладываем овощи, сверху кусочки рыбы, заправляем оливковым маслом.\nГотовим блюдо 20 минут.",
      "img": ""
    }

  ,{
      "star": "false",
      "id": "0207",
      "group": "Вторые блюда",
      "title": "Куриное суфле",
      "description": "",
      "veg": "false",
      "ingredients": [
        "куриное филе: 300 гр",
        "луковица: 2 шт",
        "яйца: 2 шт",
        "манная крупа: 3 ст. л.",
        "молоко: 50 мл",
        "соль, перец по вкусу"
      ],
      "steps": "Заливаем манку молоком и даём набухнуть крупе.\nЛук чистим и нарезаем.\nКуриное филе моем и режем на небольшие куски.\nПеремалываем филе вместе с луком, добавляем желтки яиц, соль, набухшую манку и перемешиваем.\nОтдельно взбиваем до пышной пены белки со щепоткой соли.\nОсторожно соединяем фарш с яичными белками.\nВозьмём силиконовые формочки, щёточкой промажем их растительным маслом и присыпем манкой.\nГотовым фаршем наполним формы и поставим в мультиварку.\nГотовим на пару 20 минут.\n",
      "img": ""
    }
  ,{
      "star": "false",
      "id": "0208",
      "group": "Вторые блюда",
      "title": "Пицца",
      "description": "",
      "veg": "false",
      "ingredients": [
        "мука: 300 гр",
        "вода: 150 мл",
        "оливковое масло: 80 мл",
        "куриное филе: 300 гр",
        "твердый сыр: 200 гр",
        "помидор: 3 шт",
        "сметана 15% жирности: 300 гр",
        "соль, перец по вкусу"
      ],
      "steps": "Смешаем масло, соль и воду.\nСделаем небольшую горку из муки, в середину вольём солевую смесь.\nЗамесим мягкое тесто, постепенно добавляя муку.\nРаскатаем тесто, перенесём его на противень.\nСмажем тесто сметаной.\nСформируем слои для пиццы.\nСначала кладём сваренное и порезанное на кусочки филе курицы, потом помидоры, порезанные кольцами.\nПосыпаем помидоры солью и тёртым сыром.\nВ разогретую до 220 градусов ставим пиццу на 5 минут.",
      "img": ""
    }

  ,{
      "star": "false",
      "id": "0209",
      "group": "Вторые блюда",
      "title": "Мясо Гармошка",
      "description": "",
      "veg": "false",
      "ingredients": [
        "говядина: 1 кг",
        "твердый сыр: 300 гр",
        "помидор: 2 шт",
        "чеснок: 1 долька",
        "соль, перец по вкусу"
      ],
      "steps": "Мясо помыть, сделать поперечные надрезы, посолить и поперчить.\nПомидоры порезать кружочками, сыр ломтиками.\nЧеснок мелко нашинковать.\nВ каждый надрез вставить сыр, помидор, немного чеснока, посолить.\nЗапекать мясо в фольге 1 час при температуре 250 градусов.\nПосле раскрыть фольгу и поставить в духовку ещё на 7 минут.",
      "img": ""
    }

  ,{
      "star": "false",
      "id": "0210",
      "group": "Вторые блюда",
      "title": "Слоеный салат",
      "description": "",
      "veg": "false",
      "ingredients": [
        "куриное филе: 300 гр",
        "твердый сыр: 150 гр",
        "зеленое яблоко: 2 шт",
        "грецкие орехи: 50 гр",
        "яйца: 3 шт",
        "натуральный йогурт: 150 мл",
        "зелень",
        "соль, перец по вкусу"
      ],
      "steps": "Яйца и филе отварить.\nОчистить яблоки от кожуры.\nФиле, яблоки и яйца порезать кубиками.\nОрехи измельчить, сыр натереть на тёрке.\nСформировать слои.\nСначала положить яйца, потом филе, затем орехи и яблоки.\nКаждый слой промазать йогуртом, смешанным с солью и перцем.\nГотовое блюдо посыпать сыром и украсить зеленью. ",
      "img": ""
    }
  ,{
      "star": "false",
      "id": "0211",
      "group": "Вторые блюда",
      "title": "Ленивые вареники",
      "description": "",
      "veg": "true",
      "ingredients": [
        "творог: 500 гр",
        "яйцо: 1 шт",
        "манная крупа: 4 ст.л.",
        "сахар: 1 ст.л.",
        "мука: 2 ст.л.",
        "натуральный йогурт: 100 мл"
      ],
      "steps": "Все ингредиенты тщательно смешать и раскатать колбаску.\nНожом отрезать небольшие кусочки и обвалять в муке.\nВ кипящую подсоленную воду положить сырые вареники и варить 5 минут.\nЗаправить «ленивые» вареники натуральным йогуртом.",
      "img": ""
    }
  ,{
      "star": "false",
      "id": "0212",
      "group": "Вторые блюда",
      "title": "Салат из грецких орехов и граната",
      "description": "",
      "veg": "true",
      "ingredients": [
        "картофель: 3 шт",
        "луковица: 1 шт",
        "гранат: 1 шт",
        "грецкие орехи: 50 гр",
        "сок лимона: 2 ст.л.",
        "растительное масло: 2 ст.л.",
        "соль"
      ],
      "steps": "Картофель отварим и порежем кубиками.\nЛук очистим и нарежем кольцами.\nПочистим гранат и измельчим грецкие орехи.\nСмешаем все ингредиенты.\nИз лимона, растительного масла и соли приготовим соус и заправим салат.",
      "img": ""
    }
  ,{
    "star": "false",
    "id": "0301",
    "group": "Десерты",
    "title": "Сырники",
    "description": "",
    "veg": "true",
    "ingredients": [
      "творог: 400 гр",
      "манная крупа: 4 ст.л.",
      "яйца: 1 шт",
      "натуральный йогурт: 100мл",
      "сахар: 2 ст.л."
          ],
    "steps": "На сырники берём сухой творог.\nВсе ингредиенты смешиваем в блендере, даём настояться смеси 5 минут, чтобы набухла манка.\nЗастилаем противень бумагой для запекания и выкладываем на него ложкой смесь в виде лепёшек.\nЗапекаем сырники 30 минут при температуре 180 градусов",
    "img": ""
    }

  ,{
      "star": "false",
      "id": "0302",
      "group": "Десерты",
      "title": "Кексы",
      "description": "",
      "veg": "true",
      "ingredients": [
        "творог: 400 гр",
        "сливочное масло: 5 гр",
        "яйца: 4 шт",
        "сахар: 2 ст.л.",
        "щепотка соли"
      ],
      "steps": "Кладём яйца, сахар в блендер и взбиваем до пышной пены.\nДобавляем творог и доводим состав до однородной массы.\nСолим.\nСмажем формы для кекса сливочным маслом и кладём в них тесто.\nГотовим кексы на водяной бане 45 минут или воспользуемся мультиваркой.",
      "img": ""
    }

  ,{
      "star": "false",
      "id": "0303",
      "group": "Десерты",
      "title": "Манник",
      "description": "",
      "veg": "true",
      "ingredients": [
        "манная крупа: 200 гр",
        "кефир 2,5% жирности: 500 мл",
        "яйца перепелиные: 5 шт",
        "сахар: 2 ст.л.",
        "сливочное масло: 5 гр",
        "щепотка соли"
      ],
      "steps": "Смешиваем кефир с манной крупой и оставляем на 40 минут для набухания.\nВзбиваем сахар с яйцами и солью до однородной массы.\nЯичную смесь тщательно смешиваем с манкой.\nСмазываем форму сливочным маслом и выкладываем в неё тесто.\nВыпекаем при 180 градусах 40 минут",
      "img": ""
    }
  ,{
      "star": "false",
      "id": "0304",
      "group": "Десерты",
      "title": "Пирог с яблоками",
      "description": "",
      "veg": "true",
      "ingredients": [
        "мука: 2 стакана",
        "кефир 2,5% жирности: 2 стакана",
        "яйца перепелиные: 5 шт",
        "сахар: 2 ч.л.",
        "сода: 2/3 ч.л.",
        "зеленое яблоко: 2шт"
      ],
      "steps": "Кефир смешать с сахаром.\nВ муку добавить соду и высыпать в кефирную смесь, тщательно перемешать при помощи миксера.\nПодержать тесто в тёплом месте, дождаться появления пузырьков.\nПомыть и очистить от кожуры и сердцевины яблоки, порезать их на дольки.\nТесто вылить в форму, сверху выложить подготовленные яблоки.\nВыпекать в духовке 40 минут, разогретой до 200 градусов",
      "img": ""
    }

  ,{
      "star": "false",
      "id": "0305",
      "group": "Десерты",
      "title": "Чизкейк",
      "description": "",
      "veg": "true",
      "ingredients": [
        "обезжиренный творог: 400 гр",
        "галетное печенье: 200 гр",
        "натуральный йогурт: 300 мл",
        "натуральный яблочный сок: 4 ст.л.",
        "куриное яйцо: 1 шт",
        "картофельный крахмал: 2 ст.л.",
        "сахар: 3 ст.л",
        "сливочное масло: 1 ст.л.",
        "половина лимона"
      ],
      "steps": "В блендере измельчаем печенье и добавляем к нему яблочный сок.\nДно формы смазываем сливочным маслом, затем укладываем измельчённое печенье хорошо утрамбуем и ставим форму в холодильник на час.\nСмешиваем творог с йогуртом и сахаром.\nНатираем на тёрке цедру половины лимона и выдавливаем сок.\nДобавляем лимон в творожную массу и выливаем полученное тесто в форму с печеньем.\nЯйцо взбиваем с крахмалом, полученную массу распределяем сверху по тесту.\nФорму с тестом ставим в ёмкость с кипятком и отправляем в духовку, разогретую до 180 градусов на один час.\nГотовый чизкейк оставим остывать в выключенной духовке.",
      "img": ""
    }
  ,{
      "star": "false",
      "id": "0306",
      "group": "Десерты",
      "title": "Йогуртное мороженое",
      "description": "",
      "veg": "true",
      "ingredients": [
        "натуральный йогурт: 500 мл",
        "черника: 200 гр",
        "натуральный варенье: 1ч.л."
      ],
      "steps": "Измельчить в блендере чернику.\nВ большой ёмкости смешать пюре из черники и йогурт.\nЗакрыть ёмкость крышкой и убрать в морозильник на один час.\nВынуть ёмкость из морозильника и взбить блендером. Проделать так ещё 3 раза.\nПосле загустения вынуть десерт и разложить по креманкам.\nПолить вареньем",
      "img": ""
    }
  ,{
      "star": "false",
      "id": "0307",
      "group": "Десерты",
      "title": "Гречневые блины",
      "description": "",
      "veg": "true",
      "ingredients": [
        "гречневая мука: 1 стакан",
        "пшеничная мука: 1 стакан",
        "вода: 3 стакан",
        "сахар: 1 ст.л.",
        "сухие дрожжи: 5 гр",
        "растительное масло: 100 мл",
        "соль"
      ],
      "steps": "В ёмкость наливаем полчашки холодной воды и всыпаем полчашки гречневой муки. Перемешиваем, чтобы не было комков.\nПолторы чашки воды кипятим и потихоньку вливаем в ёмкость, постоянно помешивая.\nДобавляем дрожжи, сахар и соль.\nЗатем маленькими порциями всыпаем оставшуюся муку.\nВыливаем третий стакан холодной воды в ёмкость и вымешиваем тесто.\nЗакрываем крышкой и ждём, когда оно начнёт подниматься.\nТесто больше мешать нельзя.\nНаливаем в сковородку растительное масло, печём блины.",
      "img": ""
    }
  ,{
      "star": "false",
      "id": "0401",
      "group": "Напитки",
      "title": "Компот из сухофруктов",
      "description": "",
      "veg": "true",
      "ingredients": [
        "яблоки",
        "абрикосы",
        "груши"
      ],
      "steps": "Все сухофрукты тщательно моем, перебираем и заливаем литром воды.\nВарим 30 минут.\nДобавляем сахар по вкусу.",
      "img": ""
    }

  ,{
      "star": "false",
      "id": "0402",
      "group": "Напитки",
      "title": "Морс из ягод",
      "description": "",
      "veg": "true",
      "ingredients": [
        "брусника: 50 гр",
        "клюква: 50 гр",
        "смородина: 50 гр",
        "сахар: 3 ст.л."
      ],
      "steps": "Все ягоды моем и перебираем.\nОтжимаем ягоды через марлю или перетираем через сито.\nСмешиваем ягоды и воду, добавляем сахар",
      "img": ""
    }
  ,{
      "star": "false",
      "id": "0403",
      "group": "Напитки",
      "title": "Смузи",
      "description": "",
      "veg": "true",
      "ingredients": [
        "банан: 2 шт",
        "черника: 100 гр",
        "натуральный йогурт: 150 мл",
        "творог 5% жирности: 100 гр"
      ],
      "steps": "Моем чернику и очищаем бананы от кожуры.\nКладём в блендер бананы, чернику, творог и измельчаем.\nДобавляем йогурт.",
      "img": ""
    }
  ,{
      "star": "false",
      "id": "0501",
      "group": "Рецепты для повышения лактации",
      "title": "Молоко с орехами",
      "description": "",
      "veg": "true",
      "ingredients": [
        "грецкие орехи: 5 шт",
        "молоко: 500 мл"
      ],
      "steps": "Грецкие орехи измельчить.\nМолоко закипятить.\nЗасыпать орехи в термос и залить молоком.\nНастаивать 3 часа.\nПить молоко перед кормлением в тёплом виде.",
      "img": ""
    }

  ,{
      "star": "false",
      "id": "0502",
      "group": "Рецепты для повышения лактации",
      "title": "Укропные семена",
      "description": "",
      "veg": "true",
      "ingredients": [
        "сухие семена укропа: 1 ст.л.",
        "вода: 1 стакан "
      ],
      "steps": "Укропные семена залить стаканом кипятка.\nНастаивать два часа.\nПроцедить.\nПить тёплый настой по полстакана два раза в день.\n",
      "img": ""
    }

  ,{
      "star": "false",
      "id": "0503",
      "group": "Рецепты для повышения лактации",
      "title": "Морковь с молоком",
      "description": "",
      "veg": "true",
      "ingredients": [
        "морковь: 1 шт",
        "молоко: 1 стакан "
      ],
      "steps": "Морковь натереть на самой мелкой тёрке или измельчить в блендере.\nЗалить стаканом кипячёного молока.\nОстудить напиток до комнатной температуры и пить два раза в день",
      "img": ""
    }
    ,{
      "star": "false",
      "id": "0201",
      "group": "абычто",
      "title": "рецепт 1го абычто",
      "description": "18+",
      "veg": "false",
      "ingredients": [
        "инг1: 100 г.",
        "инг2: 2 шт.",
        "инг3: 30 мг.",
        "инг4: 400 мл.",
        "водки: 1/2 стакана (можно по вкусу)"
      ],
      "steps": "взять\nпо вкусу\nне взбалтывать",
      "img": ""
    }

  ]
}